AUTHORS
LICENSE
MANIFEST.in
README.rst
setup.py
django_filebrowser_no_grappelli_emencia.egg-info/PKG-INFO
django_filebrowser_no_grappelli_emencia.egg-info/SOURCES.txt
django_filebrowser_no_grappelli_emencia.egg-info/dependency_links.txt
django_filebrowser_no_grappelli_emencia.egg-info/not-zip-safe
django_filebrowser_no_grappelli_emencia.egg-info/top_level.txt
docs/Makefile
docs/admin.rst
docs/api.rst
docs/changelog.rst
docs/conf.py
docs/faq.rst
docs/fieldswidgets.rst
docs/filelisting.rst
docs/fileobject.rst
docs/help.rst
docs/index.rst
docs/quickstart.rst
docs/releasenotes.rst
docs/settings.rst
docs/translation.rst
docs/troubleshooting.rst
docs/versions.rst
filebrowser/__init__.py
filebrowser/actions.py
filebrowser/base.py
filebrowser/decorators.py
filebrowser/fields.py
filebrowser/forms.py
filebrowser/functions.py
filebrowser/models.py
filebrowser/settings.py
filebrowser/signals.py
filebrowser/sites.py
filebrowser/storage.py
filebrowser/urls.py
filebrowser/utils.py
filebrowser/views.py
filebrowser/widgets.py
filebrowser/locale/az/LC_MESSAGES/django.mo
filebrowser/locale/az/LC_MESSAGES/django.po
filebrowser/locale/bg_BG/LC_MESSAGES/django.mo
filebrowser/locale/bg_BG/LC_MESSAGES/django.po
filebrowser/locale/cs/LC_MESSAGES/django.mo
filebrowser/locale/cs/LC_MESSAGES/django.po
filebrowser/locale/de/LC_MESSAGES/django.mo
filebrowser/locale/de/LC_MESSAGES/django.po
filebrowser/locale/en/LC_MESSAGES/django.mo
filebrowser/locale/en/LC_MESSAGES/django.po
filebrowser/locale/es/LC_MESSAGES/django.mo
filebrowser/locale/es/LC_MESSAGES/django.po
filebrowser/locale/fa/LC_MESSAGES/django.mo
filebrowser/locale/fa/LC_MESSAGES/django.po
filebrowser/locale/fr/LC_MESSAGES/django.mo
filebrowser/locale/fr/LC_MESSAGES/django.po
filebrowser/locale/is/LC_MESSAGES/django.mo
filebrowser/locale/is/LC_MESSAGES/django.po
filebrowser/locale/it/LC_MESSAGES/django.mo
filebrowser/locale/it/LC_MESSAGES/django.po
filebrowser/locale/ja/LC_MESSAGES/django.mo
filebrowser/locale/ja/LC_MESSAGES/django.po
filebrowser/locale/ja_JP/LC_MESSAGES/django.mo
filebrowser/locale/ja_JP/LC_MESSAGES/django.po
filebrowser/locale/mn/LC_MESSAGES/django.mo
filebrowser/locale/mn/LC_MESSAGES/django.po
filebrowser/locale/nb/LC_MESSAGES/django.mo
filebrowser/locale/nb/LC_MESSAGES/django.po
