Metadata-Version: 1.1
Name: django-filebrowser-no-grappelli-emencia
Version: 3.5.7.1
Summary: Media-Management no Grappelli
Home-page: http://django-filebrowser.readthedocs.org
Author: Patrick Kranzlmueller, Axel Swoboda (vonautomatisch)
Author-email: office@vonautomatisch.at
License: BSD
Platform: UNKNOWN
Classifier: Development Status :: 5 - Production/Stable
Classifier: Environment :: Web Environment
Classifier: Framework :: Django
Classifier: Intended Audience :: Developers
Classifier: License :: OSI Approved :: BSD License
Classifier: Operating System :: OS Independent
Classifier: Programming Language :: Python
Classifier: Programming Language :: Python :: 2
Classifier: Programming Language :: Python :: 2.6
Classifier: Programming Language :: Python :: 2.7
Classifier: Programming Language :: Python :: 3
Classifier: Programming Language :: Python :: 3.1
Classifier: Programming Language :: Python :: 3.2
Classifier: Programming Language :: Python :: 3.3
